MANIFEST.in
README.md
setup.py
django_dynamicresponse.egg-info/PKG-INFO
django_dynamicresponse.egg-info/SOURCES.txt
django_dynamicresponse.egg-info/dependency_links.txt
django_dynamicresponse.egg-info/top_level.txt
dynamicresponse/__init__.py
dynamicresponse/emitters.py
dynamicresponse/json_response.py
dynamicresponse/response.py
dynamicresponse/middleware/__init__.py
dynamicresponse/middleware/api.py
dynamicresponse/middleware/dynamicformat.py