Metadata-Version: 1.0
Name: django-dynamicresponse
Version: 0.4.1
Summary: Lightweight framework for easily providing REST APIs for web apps built with Django.
Home-page: https://github.com/funkbit/django-dynamicresponse
Author: Funkbit AS
Author-email: post@funkbit.no
License: BSD
Platform: UNKNOWN
Classifier: Development Status :: 4 - Beta
Classifier: Framework :: Django
Classifier: Intended Audience :: Developers
Classifier: License :: OSI Approved :: BSD License
Classifier: Programming Language :: Python
Classifier: Programming Language :: Python :: 2.6
Classifier: Programming Language :: Python :: 2.7
